LICENSE.txt
MANIFEST.in
README.rst
setup.cfg
setup.py
versioneer.py
cyflann/__init__.py
cyflann/_version.py
cyflann/extensions.py
cyflann/flann.pxd
cyflann/flann_info.py
cyflann/index.c
cyflann/index.pxd
cyflann/index.pyx
cyflann.egg-info/PKG-INFO
cyflann.egg-info/SOURCES.txt
cyflann.egg-info/dependency_links.txt
cyflann.egg-info/not-zip-safe
cyflann.egg-info/top_level.txt
cyflann/tests/__init__.py
cyflann/tests/test_extension.py
cyflann/tests/test_pickle.py
cyflann/tests/test_vs_pyflann.py