Metadata-Version: 1.1
Name: cyflann
Version: 0.2.4
Summary: A Cython-based interface to the FLANN nearest neighbors library.
Home-page: https://github.com/dougalsutherland/cyflann
Author: Dougal J. Sutherland
Author-email: dougal@gmail.com
License: BSD 3-clause
Platform: UNKNOWN
Classifier: Development Status :: 2 - Pre-Alpha
Classifier: Intended Audience :: Science/Research
Classifier: License :: OSI Approved :: BSD License
Classifier: Operating System :: OS Independent
Classifier: Programming Language :: Python :: 2
Classifier: Programming Language :: Python :: 2.7
Classifier: Programming Language :: Python :: 3.5
Classifier: Programming Language :: Python :: 3.6
Classifier: Programming Language :: Cython
Classifier: Programming Language :: Python :: Implementation :: CPython
